api_bastion/__init__.py
api_bastion-0.0.1.dist-info/METADATA
api_bastion-0.0.1.dist-info/WHEEL
api_bastion-0.0.1.dist-info/licenses/LICENSE
api_bastion-0.0.1.dist-info/RECORD
